{"identifier": "", "motion_text": "(H) PASSED Y39 A1 #1324", "motion_classification": ["passage"], "start_date": "2025-05-19", "result": "pass", "organization": "~{\"classification\": \"lower\"}", "legislative_session": "34", "bill": "80120bcc-6713-11f1-bb82-123ab6602066", "bill_action": null, "bill_identifier": "HB101", "votes": [], "counts": [{"option": "yes", "value": 39}, {"option": "no", "value": 0}, {"option": "other", "value": 1}], "sources": [{"url": "https://www.akleg.gov/basis/Journal/Pages/34?Chamber=H&Bill=HB101&Page=01324#1324", "note": ""}], "extras": {}, "_id": "801286f6-6713-11f1-bb82-123ab6602066"}