{"identifier": "", "motion_text": "(H) AM NO 1 FAILED Y12 N25 E3 #\r\n                                                    699", "motion_classification": ["passage"], "start_date": "2025-04-11", "result": "fail", "organization": "~{\"classification\": \"lower\"}", "legislative_session": "34", "bill": "c458be16-da5a-11f0-9fe1-82edf9cc2b02", "bill_action": null, "bill_identifier": "HB75", "votes": [], "counts": [{"option": "yes", "value": 12}, {"option": "no", "value": 25}, {"option": "other", "value": 3}], "sources": [{"url": "https://www.akleg.gov/basis/Journal/Pages/34?Chamber=H&Bill=HB75&Page=00699#AM1", "note": ""}], "extras": {}, "_id": "c4592766-da5a-11f0-9fe1-82edf9cc2b02"}