{"identifier": "", "motion_text": "(H) PASSED Y39 E1 #1241", "motion_classification": ["passage"], "start_date": "2025-05-16", "result": "pass", "organization": "~{\"classification\": \"lower\"}", "legislative_session": "34", "bill": "687cb66c-0339-11f1-b5b1-cef30c4bbbb3", "bill_action": null, "bill_identifier": "HB23", "votes": [], "counts": [{"option": "yes", "value": 39}, {"option": "no", "value": 0}, {"option": "other", "value": 1}], "sources": [{"url": "https://www.akleg.gov/basis/Journal/Pages/34?Chamber=H&Bill=HB23&Page=01241#1241", "note": ""}], "extras": {}, "_id": "687d2624-0339-11f1-b5b1-cef30c4bbbb3"}