{"identifier": "", "motion_text": "(S) CONCUR AM OF (H) Y20 N- #2870", "motion_classification": ["passage"], "start_date": "2026-05-20", "result": "pass", "organization": "~{\"classification\": \"upper\"}", "legislative_session": "34", "bill": "62b0ebda-867f-11f1-8627-22b803284b95", "bill_action": null, "bill_identifier": "SB79", "votes": [], "counts": [{"option": "yes", "value": 20}, {"option": "no", "value": 0}, {"option": "other", "value": 0}], "sources": [{"url": "https://www.akleg.gov/basis/Journal/Pages/34?Chamber=S&Bill=SB79&Page=02870#2870", "note": ""}], "extras": {}, "_id": "62b1f00c-867f-11f1-8627-22b803284b95"}