{"identifier": "", "motion_text": "(H) PASSED Y38 N2 #2442", "motion_classification": ["passage"], "start_date": "2026-05-07", "result": "pass", "organization": "~{\"classification\": \"lower\"}", "legislative_session": "34", "bill": "d08f2966-84ed-11f1-ba8d-b23d262ffbd5", "bill_action": null, "bill_identifier": "SB89", "votes": [], "counts": [{"option": "yes", "value": 38}, {"option": "no", "value": 2}, {"option": "other", "value": 0}], "sources": [{"url": "https://www.akleg.gov/basis/Journal/Pages/34?Chamber=H&Bill=SB89&Page=02442#2442", "note": ""}], "extras": {}, "_id": "d09024f6-84ed-11f1-ba8d-b23d262ffbd5"}