{"identifier": "", "motion_text": "(S) GOVERNOR VETO OVERRIDDEN Y43 N16 E1 #1434", "motion_classification": ["passage"], "start_date": "2025-08-02", "result": "pass", "organization": "~{\"classification\": \"upper\"}", "legislative_session": "34", "bill": "d369c6c6-fdb8-11f0-924f-6a8b8060067f", "bill_action": null, "bill_identifier": "SB183", "votes": [], "counts": [{"option": "yes", "value": 43}, {"option": "no", "value": 16}, {"option": "other", "value": 1}], "sources": [{"url": "https://www.akleg.gov/basis/Journal/Pages/34?Chamber=S&Bill=SB183&Page=01434#1434", "note": ""}], "extras": {}, "_id": "d36ac6e8-fdb8-11f0-924f-6a8b8060067f"}