{"identifier": "", "motion_text": "(H) PASSED ON RECONSIDERATION Y40 #1304", "motion_classification": ["passage"], "start_date": "2025-05-18", "result": "pass", "organization": "~{\"classification\": \"lower\"}", "legislative_session": "34", "bill": "a798f256-dd7e-11f0-861c-363b6616f99c", "bill_action": null, "bill_identifier": "SB133", "votes": [], "counts": [{"option": "yes", "value": 40}, {"option": "no", "value": 0}, {"option": "other", "value": 0}], "sources": [{"url": "https://www.akleg.gov/basis/Journal/Pages/34?Chamber=H&Bill=SB133&Page=01304#1304", "note": ""}], "extras": {}, "_id": "a79a0100-dd7e-11f0-861c-363b6616f99c"}