{"identifier": "", "motion_text": "(H) PASSED Y21 N19 #1177", "motion_classification": ["passage"], "start_date": "2025-05-13", "result": "pass", "organization": "~{\"classification\": \"lower\"}", "legislative_session": "34", "bill": "8f6d10ee-3e2d-11f1-a4ee-7e54916c9cc1", "bill_action": null, "bill_identifier": "SB57", "votes": [], "counts": [{"option": "yes", "value": 21}, {"option": "no", "value": 19}, {"option": "other", "value": 0}], "sources": [{"url": "https://www.akleg.gov/basis/Journal/Pages/34?Chamber=H&Bill=SB57&Page=01177#1177", "note": ""}], "extras": {}, "_id": "8f6ff8f4-3e2d-11f1-a4ee-7e54916c9cc1"}