{"identifier": "", "motion_text": "(S) PASSED Y20 N- #1346", "motion_classification": ["passage"], "start_date": "2025-05-19", "result": "pass", "organization": "~{\"classification\": \"upper\"}", "legislative_session": "34", "bill": "738e2aae-5cda-11f1-a5f9-c22d7fe4e34d", "bill_action": null, "bill_identifier": "HB121", "votes": [], "counts": [{"option": "yes", "value": 20}, {"option": "no", "value": 0}, {"option": "other", "value": 0}], "sources": [{"url": "https://www.akleg.gov/basis/Journal/Pages/34?Chamber=S&Bill=HB121&Page=01346#1346", "note": ""}], "extras": {}, "_id": "738ef51a-5cda-11f1-a5f9-c22d7fe4e34d"}