{"identifier": "", "motion_text": "(H) WITHDRAW FROM RLS TO CAL, RULE 18, FAILED Y19 N19 E2 #239", "motion_classification": ["passage"], "start_date": "2025-02-24", "result": "fail", "organization": "~{\"classification\": \"lower\"}", "legislative_session": "34", "bill": "c045ff48-ed36-11f0-9af6-c637c75ccd23", "bill_action": null, "bill_identifier": "HB69", "votes": [], "counts": [{"option": "yes", "value": 19}, {"option": "no", "value": 19}, {"option": "other", "value": 2}], "sources": [{"url": "https://www.akleg.gov/basis/Journal/Pages/34?Chamber=H&Bill=HB69&Page=00239#0239", "note": ""}], "extras": {}, "_id": "c0471f9a-ed36-11f0-9af6-c637c75ccd23"}