{"identifier": "", "motion_text": "(H) PASSED Y33 N6 E1 #480", "motion_classification": ["passage"], "start_date": "2025-03-17", "result": "pass", "organization": "~{\"classification\": \"lower\"}", "legislative_session": "34", "bill": "62e8355a-625c-11f1-ae02-daafce8d9d89", "bill_action": null, "bill_identifier": "HJR6", "votes": [], "counts": [{"option": "yes", "value": 33}, {"option": "no", "value": 6}, {"option": "other", "value": 1}], "sources": [{"url": "https://www.akleg.gov/basis/Journal/Pages/34?Chamber=H&Bill=HJR6&Page=00480#0480", "note": ""}], "extras": {}, "_id": "62e890ea-625c-11f1-ae02-daafce8d9d89"}