{"identifier": "", "motion_text": "(H) PASSED Y33 N4 E2 A1 #530", "motion_classification": ["passage"], "start_date": "2025-03-24", "result": "pass", "organization": "~{\"classification\": \"lower\"}", "legislative_session": "34", "bill": "fe227ad4-d86a-11f0-9955-9ac5a2e1bcdc", "bill_action": null, "bill_identifier": "HJR11", "votes": [], "counts": [{"option": "yes", "value": 33}, {"option": "no", "value": 4}, {"option": "other", "value": 3}], "sources": [{"url": "https://www.akleg.gov/basis/Journal/Pages/34?Chamber=H&Bill=HJR11&Page=00530#0530", "note": ""}], "extras": {}, "_id": "fe22d592-d86a-11f0-9955-9ac5a2e1bcdc"}