{"identifier": "", "motion_text": "(H) AM NO 15 FAILED Y15 N23 E2 #\r\n                                                    1115", "motion_classification": ["passage"], "start_date": "2025-05-10", "result": "fail", "organization": "~{\"classification\": \"lower\"}", "legislative_session": "34", "bill": "b838b084-0d70-11f1-8546-1e0a696a9910", "bill_action": null, "bill_identifier": "HB78", "votes": [], "counts": [{"option": "yes", "value": 15}, {"option": "no", "value": 23}, {"option": "other", "value": 2}], "sources": [{"url": "https://www.akleg.gov/basis/Journal/Pages/34?Chamber=H&Bill=HB78&Page=01115#AM15", "note": ""}], "extras": {}, "_id": "b83acf72-0d70-11f1-8546-1e0a696a9910"}