{"identifier": "", "motion_text": "(S) PASSED Y20 N- #860", "motion_classification": ["passage"], "start_date": "2025-04-14", "result": "pass", "organization": "~{\"classification\": \"upper\"}", "legislative_session": "34", "bill": "20f56586-1f82-11f1-b872-0af57a6f1f66", "bill_action": null, "bill_identifier": "SB40", "votes": [], "counts": [{"option": "yes", "value": 20}, {"option": "no", "value": 0}, {"option": "other", "value": 0}], "sources": [{"url": "https://www.akleg.gov/basis/Journal/Pages/34?Chamber=S&Bill=SB40&Page=00860#0860", "note": ""}], "extras": {}, "_id": "20f5a2bc-1f82-11f1-b872-0af57a6f1f66"}