{"identifier": "", "motion_text": "(H) ADVANCED TO THIRD READING Y33 N7 #1302", "motion_classification": ["passage"], "start_date": "2025-05-18", "result": "pass", "organization": "~{\"classification\": \"lower\"}", "legislative_session": "34", "bill": "6234f070-00dd-11f1-b890-bea15f6128e8", "bill_action": null, "bill_identifier": "SB133", "votes": [], "counts": [{"option": "yes", "value": 33}, {"option": "no", "value": 7}, {"option": "other", "value": 0}], "sources": [{"url": "https://www.akleg.gov/basis/Journal/Pages/34?Chamber=H&Bill=SB133&Page=01302#1302", "note": ""}], "extras": {}, "_id": "6235aab0-00dd-11f1-b890-bea15f6128e8"}