{"identifier": "", "motion_text": "(H) AM 1 TO AM 2 FAILED Y17 N22 A1 #1143", "motion_classification": ["passage"], "start_date": "2025-05-12", "result": "fail", "organization": "~{\"classification\": \"lower\"}", "legislative_session": "34", "bill": "d8ec9c6e-0014-11f1-844d-faa29a88887e", "bill_action": null, "bill_identifier": "SB57", "votes": [], "counts": [{"option": "yes", "value": 17}, {"option": "no", "value": 22}, {"option": "other", "value": 1}], "sources": [{"url": "https://www.akleg.gov/basis/Journal/Pages/34?Chamber=H&Bill=SB57&Page=01143#1143", "note": ""}], "extras": {}, "_id": "d8ee285e-0014-11f1-844d-faa29a88887e"}