{"identifier": "", "motion_text": "(H) AM NO 5 FAILED Y17 N21 E2 #\r\n                                                    1125", "motion_classification": ["passage"], "start_date": "2025-05-10", "result": "fail", "organization": "~{\"classification\": \"lower\"}", "legislative_session": "34", "bill": "fa764578-d86a-11f0-9955-9ac5a2e1bcdc", "bill_action": null, "bill_identifier": "HB13", "votes": [], "counts": [{"option": "yes", "value": 17}, {"option": "no", "value": 21}, {"option": "other", "value": 2}], "sources": [{"url": "https://www.akleg.gov/basis/Journal/Pages/34?Chamber=H&Bill=HB13&Page=01125#AM5", "note": ""}], "extras": {}, "_id": "fa774e3c-d86a-11f0-9955-9ac5a2e1bcdc"}