{"identifier": "", "motion_text": "(S) PASSED ON RECONSIDERATION Y20 N- #2802", "motion_classification": ["passage"], "start_date": "2026-05-19", "result": "pass", "organization": "~{\"classification\": \"upper\"}", "legislative_session": "34", "bill": "44370434-7f25-11f1-8427-f245a7e246c2", "bill_action": null, "bill_identifier": "HB239", "votes": [], "counts": [{"option": "yes", "value": 20}, {"option": "no", "value": 0}, {"option": "other", "value": 0}], "sources": [{"url": "https://www.akleg.gov/basis/Journal/Pages/34?Chamber=S&Bill=HB239&Page=02802#2802", "note": ""}], "extras": {}, "_id": "4438f528-7f25-11f1-8427-f245a7e246c2"}